[
  {
    "id": "1",
    "title": "How to learn COMP9323",
    "description": "This question previously had question details. You can find them in the question comments.",
    "author": "Obama",
    "tags": [
      {
        "id" : "1",
        "name":"cse"
      },
      {
        "id" : "2",
        "name":"unsw"
      }
    ],
    "postTime" : "2016-09-09 12:00:09"
  },
  {
    "id": "2",
    "title": "How to learn COMP9323",
    "description": "This question previously had question details. You can find them in the question comments.",
    "author": "Obama",
    "tags": [
      {
        "id" : "1",
        "name":"cse"
      },
      {
        "id" : "2",
        "name":"unsw"
      }
    ],
    "postTime" : "2016-09-09 12:00:09"
  },
  {
    "id": "3",
    "title": "How to learn COMP9323",
    "description": "This question previously had question details. You can find them in the question comments.",
    "author": "Obama",
    "tags": [
      {
        "id" : "1",
        "name":"cse"
      },
      {
        "id" : "2",
        "name":"unsw"
      }
    ],
    "postTime" : "2016-09-09 12:00:09"
  },
  {
    "id": "4",
    "title": "How to learn COMP9323",
    "description": "This question previously had question details. You can find them in the question comments.",
    "author": "Obama",
    "tags": [
      {
        "id" : "1",
        "name":"cse"
      },
      {
        "id" : "2",
        "name":"unsw"
      }
    ],
    "postTime" : "2016-09-09 12:00:09"
  },
  {
    "id": "5",
    "title": "How to learn COMP9323",
    "description": "This question previously had question details. You can find them in the question comments.",
    "author": "Obama",
    "tags": [
      {
        "id" : "1",
        "name":"cse"
      },
      {
        "id" : "2",
        "name":"unsw"
      }
    ],
    "postTime" : "2016-09-09 12:00:09"
  },
  {
    "id": "6",
    "title": "How to learn COMP9323",
    "description": "This question previously had question details. You can find them in the question comments.",
    "author": "Obama",
    "tags": [
      {
        "id" : "1",
        "name":"cse"
      },
      {
        "id" : "2",
        "name":"unsw"
      }
    ],
    "postTime" : "2016-09-09 12:00:09"
  },
  {
    "id": "7",
    "title": "How to learn COMP9323",
    "description": "This question previously had question details. You can find them in the question comments.",
    "author": "Obama",
    "tags": [
      {
        "id" : "1",
        "name":"cse"
      },
      {
        "id" : "2",
        "name":"unsw"
      }
    ],
    "postTime" : "2016-09-09 12:00:09"
  },
  {
    "id": "7",
    "title": "How to learn COMP9323",
    "description": "This question previously had question details. You can find them in the question comments.",
    "author": "Obama",
    "tags": [
      {
        "id" : "1",
        "name":"cse"
      },
      {
        "id" : "2",
        "name":"unsw"
      }
    ],
    "postTime" : "2016-09-09 12:00:09"
  },
  {
    "id": "8",
    "title": "How to learn COMP9323",
    "description": "This question previously had question details. You can find them in the question comments.",
    "author": "Obama",
    "tags": [
      {
        "id" : "1",
        "name":"cse"
      },
      {
        "id" : "2",
        "name":"unsw"
      }
    ],
    "postTime" : "2016-09-09 12:00:09"
  },
  {
    "id": "9",
    "title": "How to learn COMP9323",
    "description": "This question previously had question details. You can find them in the question comments.",
    "author": "Obama",
    "tags": [
      {
        "id" : "1",
        "name":"cse"
      },
      {
        "id" : "2",
        "name":"unsw"
      }
    ],
    "postTime" : "2016-09-09 12:00:09"
  },
  {
    "id": "10",
    "title": "How to learn COMP9021",
    "description": "This question previously had question details. You can find them in the question comments.",
    "author": "Tom",
    "tags": [
      {
        "id" : "1",
        "name":"java"
      },
      {
        "id" : "2",
        "name":"j2ee"
      }
    ],
    "postTime" : "2016-09-09 12:00:09"
  }
]
